LICENCE.txt
README.txt
setup.py
ArucoScanner/__init__.py
ArucoScanner.egg-info/PKG-INFO
ArucoScanner.egg-info/SOURCES.txt
ArucoScanner.egg-info/dependency_links.txt
ArucoScanner.egg-info/requires.txt
ArucoScanner.egg-info/top_level.txt